movie_scrap/__init__.py
movie_scrap/movie_scrap.py
Movie_rank-1.0.0.0.dist-info/METADATA
Movie_rank-1.0.0.0.dist-info/WHEEL
Movie_rank-1.0.0.0.dist-info/top_level.txt
Movie_rank-1.0.0.0.dist-info/RECORD
