Metadata-Version: 2.1
Name: Movie-rank
Version: 1.0.0.0
Summary: show movie rank
Home-page: https://github.com/csj0362
Author: SJ
Author-email: koreaxman@naver.com
License: MIT
Platform: UNKNOWN
Requires-Python: >=3
